<?xml version="1.0" encoding="utf-8" standalone="yes"?><records><db><record>183</record><data>00B7;MIDDLE DOT;Po;0;ON;;;;;N;;;;;;;;10;1.1</data></db>
<desc><record>183</record><data>¶= midpoint (in typography)¶= Georgian comma¶= Greek middle dot (ano teleia)¶→ (greek ano teleia - 0387)¶→ (runic single punctuation - 16EB)¶→ (bullet - 2022)¶→ (one dot leader - 2024)¶→ (hyphenation point - 2027)¶→ (bullet operator - 2219)¶→ (dot operator - 22C5)¶→ (word separator middle dot - 2E31)¶→ (katakana middle dot - 30FB)</data></desc>
</records>
